diffbot_enhance_client/__init__.py
diffbot_enhance_client/api_client.py
diffbot_enhance_client/configuration.py
diffbot_enhance_client/exceptions.py
diffbot_enhance_client/rest.py
diffbot_enhance_client/api/__init__.py
diffbot_enhance_client/api/bulk_enhance_endpoint_api.py
diffbot_enhance_client/api/enhance_live_endpoint_api.py
diffbot_enhance_client/models/__init__.py
diffbot_enhance_client/models/bulkjob_accepted.py
diffbot_enhance_client/models/bulkjob_recovery_status_response.py
diffbot_enhance_client/models/bulkjob_status.py
diffbot_enhance_client/models/bulkjob_status_response.py
diffbot_enhance_client/models/enhance_response.py
diffbot_enhance_client/models/request_error.py
diffbot_enhance_client-1.0.0.dist-info/LICENSE
diffbot_enhance_client-1.0.0.dist-info/METADATA
diffbot_enhance_client-1.0.0.dist-info/WHEEL
diffbot_enhance_client-1.0.0.dist-info/top_level.txt
diffbot_enhance_client-1.0.0.dist-info/RECORD
