Metadata-Version: 2.1
Name: diffbot-enhance-client
Version: 1.0.0
Summary: Diffbot Enhance Service
Home-page: https://github.com/diffbot/enhance-client-python
Author: OpenAPI Generator community
Author-email: support@diffbot.com
License: UNKNOWN
Keywords: OpenAPI,OpenAPI-Generator,Diffbot Enhance Service
Platform: UNKNOWN
Requires-Dist: urllib3 (>=1.15)
Requires-Dist: six (>=1.10)
Requires-Dist: certifi
Requires-Dist: python-dateutil
